panshi2task/base.py
panshi2task/client.py
panshi2task/embedding_client.py
panshi2task/grpc_gen/task_embedding_pb2.py
panshi2task/grpc_gen/task_embedding_pb2.pyi
panshi2task/grpc_gen/task_embedding_pb2_grpc.py
panshi2task/grpc_gen/task_llm_pb2.py
panshi2task/grpc_gen/task_llm_pb2.pyi
panshi2task/grpc_gen/task_llm_pb2_grpc.py
panshi2task/grpc_gen/task_paddle_pb2.py
panshi2task/grpc_gen/task_paddle_pb2.pyi
panshi2task/grpc_gen/task_paddle_pb2_grpc.py
panshi2task/grpc_gen/task_torch_pb2.py
panshi2task/grpc_gen/task_torch_pb2.pyi
panshi2task/grpc_gen/task_torch_pb2_grpc.py
panshi2task/llm_client.py
panshi2task/paddle_client.py
panshi2task/rerank_client.py
panshi2task/torch_client.py
panshi2task-0.3.0.dist-info/METADATA
panshi2task-0.3.0.dist-info/WHEEL
panshi2task-0.3.0.dist-info/RECORD
